{
   "type": "origins:multiple",
   "name": "Arcane",
   "damage":
 {
  "type": "origins:conditioned_attribute",
  "condition": {
   "type": "origins:scoreboard",
   "objective": "cumbersomecLevel",
   "comparison": "==",
   "compare_to": 1
},
   "modifier": {
       "attribute": "minecraft:generic.attack_speed",
       "value": -0.1,
       "operation": "multiply_base"
   }
},
   "magicdefence": 
   {
      "type": "origins:modify_break_speed",
      "modifier": {
          "operation": "multiply_base",
          "value": -0.1
      }
  }
}